recaptchabreaker/__init__.py
recaptchabreaker/constants.py
recaptchabreaker/main.py
recaptchabreaker/model.py
recaptchabreaker/utils.py
ReCaptchaBreaker-0.2.0.dist-info/LICENSE.md
ReCaptchaBreaker-0.2.0.dist-info/METADATA
ReCaptchaBreaker-0.2.0.dist-info/WHEEL
ReCaptchaBreaker-0.2.0.dist-info/top_level.txt
ReCaptchaBreaker-0.2.0.dist-info/RECORD
