Metadata-Version: 2.1
Name: ReCaptchaBreaker
Version: 0.2.0
Summary: An easy tool to automatically crack Google's ReCaptcha, with near-human performance.
Home-page: https://github.com/Hackear2041/ReCaptchaBreaker
Author: Hackear
License: MIT
Keywords: python recaptcha google captcha bot captchabreak
Platform: UNKNOWN
License-File: LICENSE.md
